{
  "project_info": {
    "project_number": "510240997460",
    "project_id": "flutterfirebaselearn-3b9d2",
    "storage_bucket": "flutterfirebaselearn-3b9d2.firebasestorage.app"
  },
  "client": [
    {
      "client_info": {
        "mobilesdk_app_id": "1:510240997460:android:96daabb32c33191a976dc1",
        "android_client_info": {
          "package_name": "com.example.flutter_with_firebase"
        }
      },
      "oauth_client": [],
      "api_key": [
        {
          "current_key": "AIzaSyApz4JK4l0gkvT2pwGCjXVEr6LwZPmGGU0"
        }
      ],
      "services": {
        "appinvite_service": {
          "other_platform_oauth_client": []
        }
      }
    }
  ],
  "configuration_version": "1"
}